example/__init__.py
phasereset/__init__.py
phasereset/phase_reset_index.py
tasslab-0.0.4.dist-info/LICENSE
tasslab-0.0.4.dist-info/METADATA
tasslab-0.0.4.dist-info/WHEEL
tasslab-0.0.4.dist-info/top_level.txt
tasslab-0.0.4.dist-info/RECORD
