Metadata-Version: 2.1
Name: tasslab
Version: 0.0.4
Summary: phase reset package
Home-page: https://github.com/nebojshaki/tasslab
Author: Nebo
Author-email: bozanic@stanford.edu
License: UNKNOWN
Platform: UNKNOWN
Classifier: Programming Language :: Python :: 3
Classifier: License :: OSI Approved :: MIT License
Classifier: Operating System :: Microsoft :: Windows :: Windows 10
